flexllm/__init__.py
flexllm/__main__.py
flexllm/chat_web.py
flexllm/mock.py
flexllm/serve.py
flexllm/async_api/__init__.py
flexllm/async_api/concurrent_call.py
flexllm/async_api/concurrent_executor.py
flexllm/async_api/core.py
flexllm/async_api/interface.py
flexllm/async_api/progress.py
flexllm/batch_tools/__init__.py
flexllm/batch_tools/folder_processor.py
flexllm/batch_tools/table_processor.py
flexllm/cache/__init__.py
flexllm/cache/response_cache.py
flexllm/clients/__init__.py
flexllm/clients/base.py
flexllm/clients/chain_of_thought.py
flexllm/clients/claude.py
flexllm/clients/gemini.py
flexllm/clients/llm.py
flexllm/clients/mllm.py
flexllm/clients/openai.py
flexllm/clients/pool.py
flexllm/clients/router.py
flexllm/data/SKILL.md
flexllm/data/chat_web.html
flexllm/msg_processors/__init__.py
flexllm/msg_processors/image_processor.py
flexllm/msg_processors/image_processor_helper.py
flexllm/msg_processors/messages_processor.py
flexllm/msg_processors/unified_processor.py
flexllm/pricing/__init__.py
flexllm/pricing/cost_tracker.py
flexllm/pricing/data.json
flexllm/pricing/token_counter.py
flexllm/pricing/updater.py
flexllm/utils/__init__.py
flexllm/utils/core.py
flexllm/utils/llm_parser.py
flexllm-0.5.6.dist-info/METADATA
flexllm-0.5.6.dist-info/WHEEL
flexllm-0.5.6.dist-info/entry_points.txt
flexllm-0.5.6.dist-info/licenses/LICENSE
flexllm-0.5.6.dist-info/RECORD
