Metadata-Version: 2.4
Name: flexllm
Version: 0.5.6
Summary: High-performance LLM client with batch processing, caching, and checkpoint recovery
Project-URL: Homepage, https://github.com/KenyonY/flexllm
Project-URL: Repository, https://github.com/KenyonY/flexllm
Project-URL: Documentation, https://github.com/KenyonY/flexllm#readme
Project-URL: Issues, https://github.com/KenyonY/flexllm/issues
Author-email: kunyuan <beidongjiedeguang@gmail.com>
License: Apache-2.0
License-File: LICENSE
Keywords: anthropic,async,batch,cache,claude,gemini,llm,multimodal,openai
Classifier: Development Status :: 4 - Beta
Classifier: Intended Audience :: Developers
Classifier: License :: OSI Approved :: Apache Software License
Classifier: Operating System :: OS Independent
Classifier: Programming Language :: Python :: 3
Classifier: Programming Language :: Python :: 3.10
Classifier: Programming Language :: Python :: 3.11
Classifier: Programming Language :: Python :: 3.12
Classifier: Topic :: Scientific/Engineering :: Artificial Intelligence
Requires-Python: >=3.10
Requires-Dist: aiohttp>=3.8.0
Requires-Dist: aiolimiter>=1.1.0
Requires-Dist: json5>=0.9.0
Requires-Dist: loguru>=0.6.0
Requires-Dist: numpy
Requires-Dist: orjson
Requires-Dist: pillow
Requires-Dist: requests>=2.28.0
Requires-Dist: rich>=12.0.0
Requires-Dist: tqdm>=4.60.0
Provides-Extra: all
Requires-Dist: flaxkv2>=0.1.5; extra == 'all'
Requires-Dist: google-auth>=2.0.0; extra == 'all'
Requires-Dist: opencv-python; extra == 'all'
Requires-Dist: pyyaml>=6.0; extra == 'all'
Requires-Dist: tiktoken>=0.5.0; extra == 'all'
Requires-Dist: typer>=0.9.0; extra == 'all'
Provides-Extra: cache
Requires-Dist: flaxkv2>=0.1.5; extra == 'cache'
Provides-Extra: cli
Requires-Dist: pyyaml>=6.0; extra == 'cli'
Requires-Dist: typer>=0.9.0; extra == 'cli'
Provides-Extra: dev
Requires-Dist: pre-commit>=3.7.0; extra == 'dev'
Requires-Dist: pytest-asyncio>=0.20.0; extra == 'dev'
Requires-Dist: pytest>=7.0.0; extra == 'dev'
Requires-Dist: ruff>=0.8.0; extra == 'dev'
Provides-Extra: image
Requires-Dist: opencv-python; extra == 'image'
Provides-Extra: test
Requires-Dist: flaxkv2>=0.1.5; extra == 'test'
Requires-Dist: opencv-python; extra == 'test'
Requires-Dist: pandas>=1.3.0; extra == 'test'
Requires-Dist: pytest-asyncio>=0.20.0; extra == 'test'
Requires-Dist: pytest>=7.0.0; extra == 'test'
Provides-Extra: token
Requires-Dist: tiktoken>=0.5.0; extra == 'token'
Provides-Extra: vertex
Requires-Dist: google-auth>=2.0.0; extra == 'vertex'
